deepseek_local/__init__.py
deepseek_local/deepseek.py
deepseek_local/utils.py
deepseek_local-0.1.1.dist-info/LICENSE
deepseek_local-0.1.1.dist-info/METADATA
deepseek_local-0.1.1.dist-info/WHEEL
deepseek_local-0.1.1.dist-info/entry_points.txt
deepseek_local-0.1.1.dist-info/top_level.txt
deepseek_local-0.1.1.dist-info/RECORD
