Metadata-Version: 2.2
Name: deepseek_local
Version: 0.1.1
Summary: A Python library for running DeepSeek-Coder locally using Ollama.
Home-page: https://github.com/sandbox259/deepseek_local
Author: Saad Aibani
Author-email: saadaibani3@gmail.com
Classifier: Programming Language :: Python :: 3
Classifier: License :: OSI Approved :: MIT License
Classifier: Operating System :: OS Independent
Requires-Python: >=3.8
License-File: LICENSE
Requires-Dist: ollama
Dynamic: author
Dynamic: author-email
Dynamic: classifier
Dynamic: description
Dynamic: description-content-type
Dynamic: home-page
Dynamic: requires-dist
Dynamic: requires-python
Dynamic: summary
